canvas_eject/__main__.py
canvas_eject/create_project.py
canvas_eject/extract_canvas_content.py
canvas_eject-0.1.1.dist-info/licenses/LICENSE
canvas_eject-0.1.1.dist-info/METADATA
canvas_eject-0.1.1.dist-info/WHEEL
canvas_eject-0.1.1.dist-info/entry_points.txt
canvas_eject-0.1.1.dist-info/top_level.txt
canvas_eject-0.1.1.dist-info/RECORD
